matmul.v
module matmul(clk, rst, input_start, inA_flat, inB_flat, outD_flat, output_rdy, counter);
    input clk;
    input rst;
    input input_start;
    input [3:0] counter;

    input [127:0] inA_flat;
    input [127:0] inB_flat;

    output [127:0] outD_flat;
    output reg output_rdy;

    wire [31:0] inA [0:3];
    wire [31:0] inB [0:3];
    reg [31:0] outD [0:3];

    // putting inputs into arrays
    assign inA[0] = inA_flat[127:96];
    assign inA[1] = inA_flat[95:64];
    assign inA[2] = inA_flat[63:32];
    assign inA[3] = inA_flat[31:0];
    assign inB[0] = inB_flat[127:96];
    assign inB[1] = inB_flat[95:64];
    assign inB[2] = inB_flat[63:32];
    assign inB[3] = inB_flat[31:0];

    assign outD_flat[127:96] = outD[0];
    assign outD_flat[95:64] = outD[1];
    assign outD_flat[63:32] = outD[2];
    assign outD_flat[31:0] = outD[3];

    wire [127:0] elemA_row1, elemA_row2, elemA_row3, elemA_row4, elemB_row1, elemB_row2, elemB_row3, elemB_row4, acc_row1, acc_row2, acc_row3, acc_row4;
    assign elemA_row1 = {elemA[0][0], elemA[0][1], elemA[0][2], elemA[0][3]};
    assign elemA_row2 = {elemA[1][0], elemA[1][1], elemA[1][2], elemA[1][3]};
    assign elemA_row3 = {elemA[2][0], elemA[2][1], elemA[2][2], elemA[2][3]};
    assign elemA_row4 = {elemA[3][0], elemA[3][1], elemA[3][2], elemA[3][3]};
    assign elemB_row1 = {elemB[0][0], elemB[1][0], elemB[2][0], elemB[3][0]};
    assign elemB_row2 = {elemB[0][1], elemB[1][1], elemB[2][1], elemB[3][1]};
    assign elemB_row3 = {elemB[0][2], elemB[1][2], elemB[2][2], elemB[3][2]};
    assign elemB_row4 = {elemB[0][3], elemB[1][3], elemB[2][3], elemB[3][3]};
    assign acc_row1 = {acc[0][0], acc[1][0], acc[2][0], acc[3][0]};
    assign acc_row2 = {acc[0][1], acc[1][1], acc[2][1], acc[3][1]};
    assign acc_row3 = {acc[0][2], acc[1][2], acc[2][2], acc[3][2]};
    assign acc_row4 = {acc[0][3], acc[1][3], acc[2][3], acc[3][3]};


    // multiply accumulate
    reg [31:0] elemA [0:3][0:3];
    reg [31:0] elemB [0:3][0:3];
    reg [31:0] acc [0:3][0:3];
    integer k, l;
    initial begin
        for (k = 0; k < 4; k = k + 1) begin
            for (l = 0; l < 4; l = l + 1) begin
                elemA[k][l] = 0;
                elemB[k][l] = 0;
                acc[k][l] = 0;
            end
        end
    end


    generate
        genvar i;
        genvar j;
        for (i = 0; i < 4; i = i+1) begin: outerloop
            for (j = 0; j < 4; j= j+1) begin: innerloop

                always @(posedge clk) begin
                    if (i == 0) begin
                        elemA[i][j] <= inA[j];
                    end else begin
                        elemA[i][j] <= elemA[i-1][j];
                    end
                    if (j == 0) begin
                        elemB[i][j] <= inB[i];
                    end else begin
                        elemB[i][j] <= elemB[i][j-1];
                    end
                end

                always @(posedge clk) begin
                    if (rst | input_start) begin
                        acc[i][j] <= 32'd0;
                        elemA[i][j] <= 32'd0;
                        elemB[i][j] <= 32'd0;
                    end else begin
                        acc[i][j] <= acc[i][j] + (elemA[i][j] * elemB[i][j]);
                    end
                end
            end
        end
    endgenerate

    // assign output
    always @(negedge clk) begin
        if (counter >= 7 && counter <= 10) begin
            outD[0] <= acc[0][counter-7];
            outD[1] <= acc[1][counter-7];
            outD[2] <= acc[2][counter-7];
            outD[3] <= acc[3][counter-7];
            output_rdy <= 1'b1;
        end else begin
            outD[0] <= 0;
            outD[1] <= 0;
            outD[2] <= 0;
            outD[3] <= 0;
            output_rdy <= 1'b0;
        end
    end
    
endmodule

matmul_tb.v
`timescale 1ns / 1ps
module matmul_tb();
    // I/O for the FU
    reg clk = 0, rst = 0, input_start;

    wire output_rdy; 
    reg [31:0] matrixA [0:3][0:3];
    reg [31:0] matrixB [0:3][0:3];
    reg [31:0] matrixResult [0:3][0:3];

    wire [127:0] rowResult_flat;
    wire [31:0] rowResult [0:3];

    reg [31:0] inA [0:3];
    reg [31:0] inB [0:3];
    reg [3:0] counter;
    reg [2:0] index;

    // unflattening result
    assign rowResult[0] = rowResult_flat[127:96];
    assign rowResult[1] = rowResult_flat[95:64];
    assign rowResult[2] = rowResult_flat[63:32];
    assign rowResult[3] = rowResult_flat[31:0];

    // initializing stuff to 0
    integer i, j, k, l;
    initial begin
        // Assign matrixA
        matrixA[0][0] = 1;  matrixA[0][1] = 2;  matrixA[0][2] = 3;  matrixA[0][3] = 4;
        matrixA[1][0] = 5;  matrixA[1][1] = 6;  matrixA[1][2] = 7;  matrixA[1][3] = 8;
        matrixA[2][0] = 9;  matrixA[2][1] = 10; matrixA[2][2] = 11; matrixA[2][3] = 12;
        matrixA[3][0] = 13; matrixA[3][1] = 14; matrixA[3][2] = 15; matrixA[3][3] = 16;

        // Assign matrixB
        matrixB[0][0] = 2;  matrixB[0][1] = 7;  matrixB[0][2] = 9;  matrixB[0][3] = 0;
        matrixB[1][0] = 0;  matrixB[1][1] = 2;  matrixB[1][2] = 0;  matrixB[1][3] = 82;
        matrixB[2][0] = 4;  matrixB[2][1] = 0;  matrixB[2][2] = 2;  matrixB[2][3] = 0;
        matrixB[3][0] = 0;  matrixB[3][1] = 0;  matrixB[3][2] = 0;  matrixB[3][3] = 1;

        index = 0;
        counter = 0;
        for (k = 0; k < 4; k = k + 1)
            for (l = 0; l < 4; l = l + 1)
                matrixResult[k][l] = 0;

        // pulse input_start at beginning for two clock cycles
        input_start = 0;   // start low
        #5;                // optional small delay before first pulse
        input_start = 1;   // set high for one clock cycle
        @(posedge clk);    // wait for next rising edge
        @(posedge clk);
        input_start = 0;   // turn off permanently

        #700
        $finish;
    end
    

    always @(posedge clk) begin
        if (rst | input_start) begin
            counter = 0;
            index = 0;
        end else begin
            counter = counter + 1;
        end

        // hardcoding the inputs for every cycle
        case (counter)
            7'd1: begin
                inA[0] = matrixA[0][3];
                inA[1] = 32'b0;
                inA[2] = 32'b0;
                inA[3] = 32'b0;

                inB[0] = matrixB[3][0];
                inB[1] = 32'b0;
                inB[2] = 32'b0;
                inB[3] = 32'b0;
            end
            7'd2: begin
                inA[0] = matrixA[0][2];
                inA[1] = matrixA[1][3];
                inA[2] = 32'b0;
                inA[3] = 32'b0;

                inB[0] = matrixB[2][0];
                inB[1] = matrixB[3][1];
                inB[2] = 32'b0;
                inB[3] = 32'b0;
            end
            7'd3: begin
                inA[0] = matrixA[0][1];
                inA[1] = matrixA[1][2];
                inA[2] = matrixA[2][3];
                inA[3] = 32'b0;

                inB[0] = matrixB[1][0];
                inB[1] = matrixB[2][1];
                inB[2] = matrixB[3][2];
                inB[3] = 32'b0;
            end
            7'd4: begin
                inA[0] = matrixA[0][0];
                inA[1] = matrixA[1][1];
                inA[2] = matrixA[2][2];
                inA[3] = matrixA[3][3];

                inB[0] = matrixB[0][0];
                inB[1] = matrixB[1][1];
                inB[2] = matrixB[2][2];
                inB[3] = matrixB[3][3];
            end
            7'd5: begin
                inA[0] = 32'b0;
                inA[1] = matrixA[1][0];
                inA[2] = matrixA[2][1];
                inA[3] = matrixA[3][2];

                inB[0] = 32'b0;
                inB[1] = matrixB[0][1];
                inB[2] = matrixB[1][2];
                inB[3] = matrixB[2][3];
            end
            7'd6: begin
                inA[0] = 32'b0;
                inA[1] = 32'b0;
                inA[2] = matrixA[2][0];
                inA[3] = matrixA[3][1];

                inB[0] = 32'b0;
                inB[1] = 32'b0;
                inB[2] = matrixB[0][2];
                inB[3] = matrixB[1][3];
            end
            7'd7: begin
                inA[0] = 32'b0;
                inA[1] = 32'b0;
                inA[2] = 32'b0;
                inA[3] = matrixA[3][0];

                inB[0] = 32'b0;
                inB[1] = 32'b0;
                inB[2] = 32'b0;
                inB[3] = matrixB[0][3];
            end
            default: begin
                inA[0] = 32'b0;
                inA[1] = 32'b0;
                inA[2] = 32'b0;
                inA[3] = 32'b0;

                inB[0] = 32'b0;
                inB[1] = 32'b0;
                inB[2] = 32'b0;
                inB[3] = 32'b0;
            end
        endcase

        // whenever a new row is ready, fill in matrix result
        if(output_rdy) begin
            for (j = 0; j < 4; j = j + 1) begin : assign_row
                matrixResult[index][j] = rowResult[j];
            end
            index = index + 1;
        end
    end

    wire [127:0] flat_A, flat_B;
    assign flat_A = {inA[0], inA[1], inA[2], inA[3]};
    assign flat_B = {inB[0], inB[1], inB[2], inB[3]};
    matmul matmultest(.clk(clk), .rst(rst), .input_start(input_start), .output_rdy(output_rdy), .outD_flat(rowResult_flat), .inA_flat(flat_A), .inB_flat(flat_B), .counter(counter));

    always 
    	#20 clk = !clk;
    
    // displaying matrix output
    always @(posedge output_rdy) begin
        #5;
        $display("matrixA:");
        for (i = 0; i < 4; i = i + 1) begin
            $write("[ ");
            for (j = 0; j < 4; j = j + 1) begin
                $write("%0d ", matrixA[i][j]);
            end
            $write("]\n");
        end

        $display("matrixB:");
        for (i = 0; i < 4; i = i + 1) begin
            $write("[ ");
            for (j = 0; j < 4; j = j + 1) begin
                $write("%0d ", matrixB[i][j]);
            end
            $write("]\n");
        end
    end
    always @(posedge clk) begin
        if (output_rdy) begin
            #5
            $display("matrixResult:");
            for (i = 0; i < 4; i = i + 1) begin
                $write("[ ");
                for (j = 0; j < 4; j = j + 1) begin
                    $write("%0d ", matrixResult[i][j]);
                end
                $write("]\n");
            end
        end
    end
    
    // Define output waveform properties
    initial begin
        // output file name
        $dumpfile("matmul.vcd");
        // module to capture and what level, 0 means all wires
        $dumpvars(0, matmul_tb);
    end

endmodule

matmul.vcd
$date
	Sat Oct 25 20:22:34 2025
$end
$version
	Icarus Verilog
$end
$timescale
	1ps
$end
$scope module matmul_tb $end
$var wire 128 ! rowResult_flat [127:0] $end
$var wire 1 " output_rdy $end
$var wire 128 # flat_B [127:0] $end
$var wire 128 $ flat_A [127:0] $end
$var reg 1 % clk $end
$var reg 4 & counter [3:0] $end
$var reg 3 ' index [2:0] $end
$var reg 1 ( input_start $end
$var reg 1 ) rst $end
$var integer 32 * i [31:0] $end
$var integer 32 + j [31:0] $end
$var integer 32 , k [31:0] $end
$var integer 32 - l [31:0] $end
$scope module matmultest $end
$var wire 1 % clk $end
$var wire 4 . counter [3:0] $end
$var wire 128 / inA_flat [127:0] $end
$var wire 128 0 inB_flat [127:0] $end
$var wire 1 ( input_start $end
$var wire 1 ) rst $end
$var wire 128 1 outD_flat [127:0] $end
$var wire 128 2 elemB_row4 [127:0] $end
$var wire 128 3 elemB_row3 [127:0] $end
$var wire 128 4 elemB_row2 [127:0] $end
$var wire 128 5 elemB_row1 [127:0] $end
$var wire 128 6 elemA_row4 [127:0] $end
$var wire 128 7 elemA_row3 [127:0] $end
$var wire 128 8 elemA_row2 [127:0] $end
$var wire 128 9 elemA_row1 [127:0] $end
$var wire 128 : acc_row4 [127:0] $end
$var wire 128 ; acc_row3 [127:0] $end
$var wire 128 < acc_row2 [127:0] $end
$var wire 128 = acc_row1 [127:0] $end
$var reg 1 " output_rdy $end
$var integer 32 > k [31:0] $end
$var integer 32 ? l [31:0] $end
$scope begin outerloop[0] $end
$var parameter 2 @ i $end
$scope begin innerloop[0] $end
$var parameter 2 A j $end
$upscope $end
$scope begin innerloop[1] $end
$var parameter 2 B j $end
$upscope $end
$scope begin innerloop[2] $end
$var parameter 3 C j $end
$upscope $end
$scope begin innerloop[3] $end
$var parameter 3 D j $end
$upscope $end
$upscope $end
$scope begin outerloop[1] $end
$var parameter 2 E i $end
$scope begin innerloop[0] $end
$var parameter 2 F j $end
$upscope $end
$scope begin innerloop[1] $end
$var parameter 2 G j $end
$upscope $end
$scope begin innerloop[2] $end
$var parameter 3 H j $end
$upscope $end
$scope begin innerloop[3] $end
$var parameter 3 I j $end
$upscope $end
$upscope $end
$scope begin outerloop[2] $end
$var parameter 3 J i $end
$scope begin innerloop[0] $end
$var parameter 2 K j $end
$upscope $end
$scope begin innerloop[1] $end
$var parameter 2 L j $end
$upscope $end
$scope begin innerloop[2] $end
$var parameter 3 M j $end
$upscope $end
$scope begin innerloop[3] $end
$var parameter 3 N j $end
$upscope $end
$upscope $end
$scope begin outerloop[3] $end
$var parameter 3 O i $end
$scope begin innerloop[0] $end
$var parameter 2 P j $end
$upscope $end
$scope begin innerloop[1] $end
$var parameter 2 Q j $end
$upscope $end
$scope begin innerloop[2] $end
$var parameter 3 R j $end
$upscope $end
$scope begin innerloop[3] $end
$var parameter 3 S j $end
$upscope $end
$upscope $end
$upscope $end
$scope begin assign_row $end
$upscope $end
$upscope $end
$enddefinitions $end
$comment Show the parameter values. $end
$dumpall
b11 S
b10 R
b1 Q
b0 P
b11 O
b11 N
b10 M
b1 L
b0 K
b10 J
b11 I
b10 H
b1 G
b0 F
b1 E
b11 D
b10 C
b1 B
b0 A
b0 @
$end
#0
$dumpvars
b100 ?
b100 >
b0 =
b0 <
b0 ;
b0 :
b0 9
b0 8
b0 7
b0 6
b0 5
b0 4
b0 3
b0 2
b0 1
bx 0
bx /
b0 .
b100 -
b100 ,
bx +
bx *
0)
0(
b0 '
b0 &
0%
bx $
bx #
0"
b0 !
$end
#5000
1(
#20000
bx 9
bx 5
b0 #
b0 0
b0 $
b0 /
1%
#40000
0%
#60000
b0 8
b0 4
b0 5
b0 9
0(
1%
#80000
0%
#100000
b100000000000000000000000000000000000000000000000000000000000000000000000000000000000000000000000000 $
b100000000000000000000000000000000000000000000000000000000000000000000000000000000000000000000000000 /
b1 &
b1 .
1%
#120000
0%
#140000
b100000000000000000000000000000000000000000000000000000000000000000000000000000000000000000000000000 9
b100000000000000000000000000000000000000000000000000000000000000000000000000000000000000000000000000 #
b100000000000000000000000000000000000000000000000000000000000000000000000000000000000000000000000000 0
b11000000000000000000000000000010000000000000000000000000000000000000000000000000000000000000000000 $
b11000000000000000000000000000010000000000000000000000000000000000000000000000000000000000000000000 /
b10 &
b10 .
1%
#160000
0%
#180000
b100000000000000000000000000000000000000000000000000000000000000000000000000000000000000000000000000 5
b11000000000000000000000000000010000000000000000000000000000000000000000000000000000000000000000000 9
b100000000000000000000000000000000000000000000000000000000000000000000000000000000000000000000000000 8
b0 #
b0 0
b10000000000000000000000000000001110000000000000000000000000000110000000000000000000000000000000000 $
b10000000000000000000000000000001110000000000000000000000000000110000000000000000000000000000000000 /
b11 &
b11 .
1%
#200000
0%
#220000
b100000000000000000000000000000000000000000000000000000000000000000000000000000000000000000000000000 7
b11000000000000000000000000000010000000000000000000000000000000000000000000000000000000000000000000 8
b100000000000000000000000000000000000000000000000000000000000000000000000000000000000000000000000000 4
b1100000000000000000000000000000000000000000000000000000000000000000000000000000000000000000000000000 =
b0 5
b10000000000000000000000000000001110000000000000000000000000000110000000000000000000000000000000000 9
b10000000000000000000000000000000100000000000000000000000000000001000000000000000000000000000000001 #
b10000000000000000000000000000000100000000000000000000000000000001000000000000000000000000000000001 0
b1000000000000000000000000000001100000000000000000000000000000101100000000000000000000000000010000 $
b1000000000000000000000000000001100000000000000000000000000000101100000000000000000000000000010000 /
b100 &
b100 .
1%
#240000
0%
#260000
b0 4
b11100000000000000000000000000000000000000000000000000000000000000000000000000000000000000000000000000 <
b100000000000000000000000000000000000000000000000000000000000000000000000000000000000000000000000000 3
b1000000000000000000000000000001100000000000000000000000000000101100000000000000000000000000010000 9
b10000000000000000000000000000001110000000000000000000000000000110000000000000000000000000000000000 8
b11000000000000000000000000000010000000000000000000000000000000000000000000000000000000000000000000 7
b10000000000000000000000000000000100000000000000000000000000000001000000000000000000000000000000001 5
b100000000000000000000000000000000000000000000000000000000000000000000000000000000000000000000000000 6
b1110000000000000000000000000000000000000000000000000000000000000000 #
b1110000000000000000000000000000000000000000000000000000000000000000 0
b1010000000000000000000000000000101000000000000000000000000000001111 $
b1010000000000000000000000000000101000000000000000000000000000001111 /
b101 &
b101 .
1%
#280000
0%
#300000
b11000000000000000000000000000010000000000000000000000000000000000000000000000000000000000000000000 6
b10000000000000000000000000000001110000000000000000000000000000110000000000000000000000000000000000 7
b1000000000000000000000000000001100000000000000000000000000000101100000000000000000000000000010000 8
b100000000000000000000000000000000000000000000000000000000000000000000000000000000000000000000000000 2
b101100000000000000000000000000000000000000000000000000000000000000000000000000000000000000000000000000 ;
b0 3
b10000000000000000000000000000000100000000000000000000000000000001000000000000000000000000000000001 4
b1110000000000000000000000000000001000000000000000000000000000000011000000000000000000000000000000100 =
b1110000000000000000000000000000000000000000000000000000000000000000 5
b1010000000000000000000000000000101000000000000000000000000000001111 9
b100100000000000000000000000001010010 #
b100100000000000000000000000001010010 0
b100100000000000000000000000000001110 $
b100100000000000000000000000000001110 /
b110 &
b110 .
1%
#320000
0%
#340000
b0 2
b100100000000000000000000000000001110 9
b111100000000000000000000000000000000000000000000000000000000000000000000000000000000000000000000000000 :
b1110000000000000000000000000000010110000000000000000000000000000011000000000000000000000000000000100 =
b1010000000000000000000000000000101000000000000000000000000000001111 8
b1000000000000000000000000000001100000000000000000000000000000101100000000000000000000000000010000 7
b100100000000000000000000000001010010 5
b1110000000000000000000000000000000000000000000000000000000000000000 4
b100110000000000000000000000000000011000000000000000000000000000000111000000000000000000000000000001000 <
b10000000000000000000000000000000100000000000000000000000000000001000000000000000000000000000000001 3
b10000000000000000000000000000001110000000000000000000000000000110000000000000000000000000000000000 6
b0 #
b0 0
b1101 $
b1101 /
b111 &
b111 .
1%
#360000
1"
b1110000000000000000000000000000010110000000000000000000000000000011000000000000000000000000000000100 !
b1110000000000000000000000000000010110000000000000000000000000000011000000000000000000000000000000100 1
0%
#365000
b100 +
b100 *
#380000
b1000000000000000000000000000001100000000000000000000000000000101100000000000000000000000000010000 6
b1110000000000000000000000000000010110000000000000000000000000000111100000000000000000000000010101000 =
b0 5
b1010000000000000000000000000000101000000000000000000000000000001111 7
b100110000000000000000000000000001011110000000000000000000000000000111000000000000000000000000000001000 <
b100100000000000000000000000001010010 4
b100100000000000000000000000000001110 8
b10000000000000000000000000000000100000000000000000000000000000001000000000000000000000000000000001 2
b111110000000000000000000000000000101000000000000000000000000000001011000000000000000000000000000001100 ;
b1110000000000000000000000000000000000000000000000000000000000000000 3
b1101 9
b1 '
b100 +
b0 $
b0 /
b1000 &
b1000 .
1%
#385000
b100 +
b100 *
#400000
b100110000000000000000000000000001011110000000000000000000000000000111000000000000000000000000000001000 !
b100110000000000000000000000000001011110000000000000000000000000000111000000000000000000000000000001000 1
0%
#420000
b0 9
b111110000000000000000000000000010100110000000000000000000000000001011000000000000000000000000000001100 ;
b1101 8
b100100000000000000000000000000001110 7
b0 4
b100110000000000000000000000000001011110000000000000000000000000011101100000000000000000000000111110100 <
b100100000000000000000000000001010010 3
b1110000000000000000000000000000000000000000000000000000000000000000 2
b1010000000000000000000000000000101000000000000000000000000000001111 6
b1010110000000000000000000000000000111000000000000000000000000000001111000000000000000000000000000010000 :
b10 '
b100 +
b1001 &
b1001 .
1%
#425000
b100 +
b100 *
#440000
b111110000000000000000000000000010100110000000000000000000000000001011000000000000000000000000000001100 !
b111110000000000000000000000000010100110000000000000000000000000001011000000000000000000000000000001100 1
0%
#460000
b100100000000000000000000000000001110 6
b111110000000000000000000000000010100110000000000000000000000000110011100000000000000000000001101000000 ;
b0 3
b1101 7
b1010110000000000000000000000000011101110000000000000000000000000001111000000000000000000000000000010000 :
b100100000000000000000000000001010010 2
b0 8
b11 '
b100 +
b1010 &
b1010 .
1%
#465000
b100 +
b100 *
#480000
b1010110000000000000000000000000011101110000000000000000000000000001111000000000000000000000000000010000 !
b1010110000000000000000000000000011101110000000000000000000000000001111000000000000000000000000000010000 1
0%
#500000
b0 7
b0 2
b1101 6
b1010110000000000000000000000000011101110000000000000000000000001001001100000000000000000000010010001100 :
b100 '
b100 +
b1011 &
b1011 .
1%
#505000
b100 +
b100 *
#520000
0"
b0 !
b0 1
0%
#540000
b0 6
b1100 &
b1100 .
1%
#560000
0%
#580000
b1101 &
b1101 .
1%
#600000
0%
#620000
b1110 &
b1110 .
1%
#640000
0%
#660000
b1111 &
b1111 .
1%
#680000
0%
#700000
b0 &
b0 .
1%
#720000
0%
#740000
b100000000000000000000000000000000000000000000000000000000000000000000000000000000000000000000000000 $
b100000000000000000000000000000000000000000000000000000000000000000000000000000000000000000000000000 /
b1 &
b1 .
1%
