max_3x3.v
module max_3x3(clk, rst, input_start, inA_flat, inB_flat, outD_flat, output_rdy, counter);
    input clk;
    input rst;
    input input_start;
    input [3:0] counter;

    // 32-bit [3x3] -> 32*3-1 = 95
    input [95:0] inA_flat;
    input [95:0] inB_flat;

    output [95:0] outD_flat;
    output reg output_rdy;

    wire [31:0] inA [0:2];
    wire [31:0] inB [0:2];
    reg [31:0] outD [0:2];

    // putting inputs into arrays
    assign inA[0] = inA_flat[95:64];
    assign inA[1] = inA_flat[63:32];
    assign inA[2] = inA_flat[31:0];
    assign inB[0] = inB_flat[95:64];
    assign inB[1] = inB_flat[63:32];
    assign inB[2] = inB_flat[31:0];

    assign outD_flat[95:64] = outD[0];
    assign outD_flat[63:32] = outD[1];
    assign outD_flat[31:0] = outD[2];

    wire [95:0] elemA_row1, elemA_row2, elemA_row3, elemB_row1, elemB_row2, elemB_row3, acc_row1, acc_row2, acc_row3;
    assign elemA_row1 = {elemA[0][0], elemA[0][1], elemA[0][2]};
    assign elemA_row2 = {elemA[1][0], elemA[1][1], elemA[1][2]};
    assign elemA_row3 = {elemA[2][0], elemA[2][1], elemA[2][2]};
    assign elemB_row1 = {elemB[0][0], elemB[1][0], elemB[2][0]};
    assign elemB_row2 = {elemB[0][1], elemB[1][1], elemB[2][1]};
    assign elemB_row3 = {elemB[0][2], elemB[1][2], elemB[2][2]};
    assign acc_row1 = {acc[0][0], acc[1][0], acc[2][0]};
    assign acc_row2 = {acc[0][1], acc[1][1], acc[2][1]};
    assign acc_row3 = {acc[0][2], acc[1][2], acc[2][2]};

    // multiply accumulate
    reg [31:0] elemA [0:2][0:2];
    reg [31:0] elemB [0:2][0:2];
    reg [31:0] acc [0:2][0:2];
    integer k, l;
    initial begin
        for (k = 0; k < 3; k = k + 1) begin
            for (l = 0; l < 3; l = l + 1) begin
                elemA[k][l] = 0;
                elemB[k][l] = 0;
                acc[k][l] = 0;
            end
        end
    end


    generate
        genvar i;
        genvar j;
        for (i = 0; i < 3; i = i+1) begin: outerloop
            for (j = 0; j < 3; j= j+1) begin: innerloop

                always @(posedge clk) begin
                    if (rst | input_start) begin
                        acc[i][j] <= 32'd0;
                        elemA[i][j] <= 32'd0;
                        elemB[i][j] <= 32'd0;
                    end else begin
                        if (i == 0) begin
                            elemA[i][j] <= inA[j];
                        end else begin
                            elemA[i][j] <= elemA[i-1][j];
                        end
                        if (j == 0) begin
                            elemB[i][j] <= inB[i];
                        end else begin
                            elemB[i][j] <= elemB[i][j-1];
                        end
                    end
                    
                    acc[i][j] <= acc[i][j] + (elemA[i][j] * elemB[i][j]);
                end
            end
        end
    endgenerate

    // assign output
    always @(negedge clk) begin
        if (counter >= 5 && counter <= 7) begin
            outD[0] <= acc[0][counter-5];
            outD[1] <= acc[1][counter-5];
            outD[2] <= acc[2][counter-5];
            output_rdy <= 1'b1;
        end else begin
            outD[0] <= 0;
            outD[1] <= 0;
            outD[2] <= 0;
            output_rdy <= 1'b0;
        end
    end
    
endmodule

max_3x3_tb.v
`timescale 1ns / 1ps
module max_3x3_tb();
    // I/O for the FU
    reg clk = 0, rst = 0, input_start;

    wire output_rdy; 
    reg [31:0] matrixA [0:2][0:2];
    reg [31:0] matrixB [0:2][0:2];
    reg [31:0] matrixResult [0:2][0:2];

    wire [95:0] rowResult_flat;
    wire [31:0] rowResult [0:2];

    reg [31:0] inA [0:2];
    reg [31:0] inB [0:2];
    reg [3:0] counter;
    reg [2:0] index;

    // unflattening result
    assign rowResult[0] = rowResult_flat[95:64];
    assign rowResult[1] = rowResult_flat[63:32];
    assign rowResult[2] = rowResult_flat[31:0];

    // For GTKWAVE visualizing better
    // wire [31:0] A1;
    // wire [31:0] A2;
    // wire [31:0] A3;
    // wire [31:0] B1;
    // wire [31:0] B2;
    // wire [31:0] B3;
    // wire [31:0] rowResult1;
    // wire [31:0] rowResult2;
    // wire [31:0] rowResult3;
    // assign A1 = flat_A[95:64];
    // assign A2 = flat_A[63:32];
    // assign A3 = flat_A[31:0];
    // assign B1 = flat_B[95:64];
    // assign B2 = flat_B[63:32];
    // assign B3 = flat_B[31:0];
    // assign rowResult1 = rowResult_flat[95:64];
    // assign rowResult2 = rowResult_flat[63:32];
    // assign rowResult3 = rowResult_flat[31:0];

    // initializing stuff to 0
    integer i, j, k, l;
    initial begin
        // Assign matrixA
        matrixA[0][0] = 1;  matrixA[0][1] = 2;  matrixA[0][2] = 3; 
        matrixA[1][0] = 4;  matrixA[1][1] = 5;  matrixA[1][2] = 6; 
        matrixA[2][0] = 7;  matrixA[2][1] = 8; matrixA[2][2] = 9;
        // Assign matrixB
        matrixB[0][0] = 1;  matrixB[0][1] = 0;  matrixB[0][2] = 0;  
        matrixB[1][0] = 0;  matrixB[1][1] = 1;  matrixB[1][2] = 0;  
        matrixB[2][0] = 0;  matrixB[2][1] = 0;  matrixB[2][2] = 1;  

        index = 0;
        counter = 0;
        for (k = 0; k < 3; k = k + 1)
            for (l = 0; l < 3; l = l + 1)
                matrixResult[k][l] = 0;

        // pulse input_start at beginning for two clock cycles
        input_start = 0;   // start low
        #5;                // optional small delay before first pulse
        input_start = 1;   // set high for one clock cycle
        @(posedge clk);    // wait for next rising edge
        @(posedge clk);
        input_start = 0;   // turn off permanently

        #700
        $finish;
    end
    

    always @(posedge clk) begin
        if (rst | input_start) begin
            counter = 0;
            index = 0;
        end else begin
            counter = counter + 1;
        end

        // hardcoding the inputs for every cycle
        case (counter)
            7'd1: begin
                inA[0] = matrixA[0][2];
                inA[1] = 32'b0;
                inA[2] = 32'b0;

                inB[0] = matrixB[2][0];
                inB[1] = 32'b0;
                inB[2] = 32'b0;
            end
            7'd2: begin
                inA[0] = matrixA[0][1];
                inA[1] = matrixA[1][2];
                inA[2] = 32'b0;

                inB[0] = matrixB[1][0];
                inB[1] = matrixB[2][1];
                inB[2] = 32'b0;
            end
            7'd3: begin
                inA[0] = matrixA[0][0];
                inA[1] = matrixA[1][1];
                inA[2] = matrixA[2][2];

                inB[0] = matrixB[0][0];
                inB[1] = matrixB[1][1];
                inB[2] = matrixB[2][2];
            end
            7'd4: begin
                inA[0] = 32'b0;
                inA[1] = matrixA[1][0];
                inA[2] = matrixA[2][1];

                inB[0] = 32'b0;
                inB[1] = matrixB[0][1];
                inB[2] = matrixB[1][2];
            end
            7'd5: begin
                inA[0] = 32'b0;
                inA[1] = 32'b0;
                inA[2] = matrixA[2][0];

                inB[0] = 32'b0;
                inB[1] = 32'b0;
                inB[2] = matrixB[0][2];
            end
            default: begin
                inA[0] = 32'b0;
                inA[1] = 32'b0;
                inA[2] = 32'b0;

                inB[0] = 32'b0;
                inB[1] = 32'b0;
                inB[2] = 32'b0;
            end
        endcase

        // whenever a new row is ready, fill in matrix result
        if(output_rdy) begin
            for (j = 0; j < 3; j = j + 1) begin : assign_row
                matrixResult[index][j] = rowResult[j];
            end
            index = index + 1;
        end
    end

    wire [95:0] flat_A, flat_B;
    assign flat_A = {inA[0], inA[1], inA[2]};
    assign flat_B = {inB[0], inB[1], inB[2]};
    max_3x3 matmultest(.clk(clk), .rst(rst), .input_start(input_start), .output_rdy(output_rdy), .outD_flat(rowResult_flat), .inA_flat(flat_A), .inB_flat(flat_B), .counter(counter));

    always 
    	#20 clk = !clk;
    
    // displaying matrix output
    always @(posedge output_rdy) begin
        #5;
        $display("matrixA:");
        for (i = 0; i < 3; i = i + 1) begin
            $write("[ ");
            for (j = 0; j < 3; j = j + 1) begin
                $write("%0d ", matrixA[i][j]);
            end
            $write("]\n");
        end

        $display("matrixB:");
        for (i = 0; i < 3; i = i + 1) begin
            $write("[ ");
            for (j = 0; j < 3; j = j + 1) begin
                $write("%0d ", matrixB[i][j]);
            end
            $write("]\n");
        end
    end
    always @(posedge clk) begin
        if (output_rdy) begin
            #5
            $display("matrixResult:");
            for (i = 0; i < 3; i = i + 1) begin
                $write("[ ");
                for (j = 0; j < 3; j = j + 1) begin
                    $write("%0d ", matrixResult[i][j]);
                end
                $write("]\n");
            end
        end
    end
    
    // Define output waveform properties
    initial begin
        // output file name
        $dumpfile("max_3x3.vcd");
        // module to capture and what level, 0 means all wires
        $dumpvars(0, max_3x3_tb);
    end

endmodule

max_3x3.vcd
$date
	Sat Nov 29 15:35:15 2025
$end
$version
	Icarus Verilog
$end
$timescale
	1ps
$end
$scope module max_3x3_tb $end
$var wire 96 ! rowResult_flat [95:0] $end
$var wire 1 " output_rdy $end
$var wire 96 # flat_B [95:0] $end
$var wire 96 $ flat_A [95:0] $end
$var reg 1 % clk $end
$var reg 4 & counter [3:0] $end
$var reg 3 ' index [2:0] $end
$var reg 1 ( input_start $end
$var reg 1 ) rst $end
$var integer 32 * i [31:0] $end
$var integer 32 + j [31:0] $end
$var integer 32 , k [31:0] $end
$var integer 32 - l [31:0] $end
$scope module matmultest $end
$var wire 1 % clk $end
$var wire 4 . counter [3:0] $end
$var wire 96 / inA_flat [95:0] $end
$var wire 96 0 inB_flat [95:0] $end
$var wire 1 ( input_start $end
$var wire 1 ) rst $end
$var wire 96 1 outD_flat [95:0] $end
$var wire 96 2 elemB_row3 [95:0] $end
$var wire 96 3 elemB_row2 [95:0] $end
$var wire 96 4 elemB_row1 [95:0] $end
$var wire 96 5 elemA_row3 [95:0] $end
$var wire 96 6 elemA_row2 [95:0] $end
$var wire 96 7 elemA_row1 [95:0] $end
$var wire 96 8 acc_row3 [95:0] $end
$var wire 96 9 acc_row2 [95:0] $end
$var wire 96 : acc_row1 [95:0] $end
$var reg 1 " output_rdy $end
$var integer 32 ; k [31:0] $end
$var integer 32 < l [31:0] $end
$scope begin outerloop[0] $end
$var parameter 2 = i $end
$scope begin innerloop[0] $end
$var parameter 2 > j $end
$upscope $end
$scope begin innerloop[1] $end
$var parameter 2 ? j $end
$upscope $end
$scope begin innerloop[2] $end
$var parameter 3 @ j $end
$upscope $end
$upscope $end
$scope begin outerloop[1] $end
$var parameter 2 A i $end
$scope begin innerloop[0] $end
$var parameter 2 B j $end
$upscope $end
$scope begin innerloop[1] $end
$var parameter 2 C j $end
$upscope $end
$scope begin innerloop[2] $end
$var parameter 3 D j $end
$upscope $end
$upscope $end
$scope begin outerloop[2] $end
$var parameter 3 E i $end
$scope begin innerloop[0] $end
$var parameter 2 F j $end
$upscope $end
$scope begin innerloop[1] $end
$var parameter 2 G j $end
$upscope $end
$scope begin innerloop[2] $end
$var parameter 3 H j $end
$upscope $end
$upscope $end
$upscope $end
$scope begin assign_row $end
$upscope $end
$upscope $end
$enddefinitions $end
$comment Show the parameter values. $end
$dumpall
b10 H
b1 G
b0 F
b10 E
b10 D
b1 C
b0 B
b1 A
b10 @
b1 ?
b0 >
b0 =
$end
#0
$dumpvars
b11 <
b11 ;
b0 :
b0 9
b0 8
b0 7
b0 6
b0 5
b0 4
b0 3
b0 2
b0 1
bx 0
bx /
b0 .
b11 -
b11 ,
bx +
bx *
0)
0(
b0 '
b0 &
0%
bx $
bx #
0"
b0 !
$end
#5000
1(
#20000
bx 7
bx 4
b0 #
b0 0
b0 $
b0 /
1%
#40000
0%
#60000
b0 6
b0 3
b0 4
b0 7
0(
1%
#80000
0%
#100000
b110000000000000000000000000000000000000000000000000000000000000000 $
b110000000000000000000000000000000000000000000000000000000000000000 /
b1 &
b1 .
1%
#120000
0%
#140000
b110000000000000000000000000000000000000000000000000000000000000000 7
b100000000000000000000000000000011000000000000000000000000000000000 $
b100000000000000000000000000000011000000000000000000000000000000000 /
b10 &
b10 .
1%
#160000
0%
#180000
b100000000000000000000000000000011000000000000000000000000000000000 7
b110000000000000000000000000000000000000000000000000000000000000000 6
b10000000000000000000000000000000100000000000000000000000000000001 #
b10000000000000000000000000000000100000000000000000000000000000001 0
b10000000000000000000000000000010100000000000000000000000000001001 $
b10000000000000000000000000000010100000000000000000000000000001001 /
b11 &
b11 .
1%
#200000
0%
#220000
b110000000000000000000000000000000000000000000000000000000000000000 5
b100000000000000000000000000000011000000000000000000000000000000000 6
b10000000000000000000000000000000100000000000000000000000000000001 4
b10000000000000000000000000000010100000000000000000000000000001001 7
b0 #
b0 0
b10000000000000000000000000000001000 $
b10000000000000000000000000000001000 /
b100 &
b100 .
1%
#240000
0%
#260000
b10000000000000000000000000000001000 7
b10000000000000000000000000000010100000000000000000000000000001001 6
b0 4
b10000000000000000000000000000001000000000000000000000000000000011 :
b10000000000000000000000000000000100000000000000000000000000000001 3
b100000000000000000000000000000011000000000000000000000000000000000 5
b111 $
b111 /
b101 &
b101 .
1%
#280000
1"
b10000000000000000000000000000001000000000000000000000000000000011 !
b10000000000000000000000000000001000000000000000000000000000000011 1
0%
#285000
b11 +
b11 *
#300000
b10000000000000000000000000000010100000000000000000000000000001001 5
b10000000000000000000000000000001000 6
b10000000000000000000000000000000100000000000000000000000000000001 2
b1000000000000000000000000000000010100000000000000000000000000000110 9
b0 3
b111 7
b1 '
b11 +
b0 $
b0 /
b110 &
b110 .
1%
#305000
b11 +
b11 *
#320000
b1000000000000000000000000000000010100000000000000000000000000000110 !
b1000000000000000000000000000000010100000000000000000000000000000110 1
0%
#340000
b0 7
b111 6
b0 2
b10000000000000000000000000000001000 5
b1110000000000000000000000000000100000000000000000000000000000001001 8
b10 '
b11 +
b111 &
b111 .
1%
#345000
b11 +
b11 *
#360000
b1110000000000000000000000000000100000000000000000000000000000001001 !
b1110000000000000000000000000000100000000000000000000000000000001001 1
0%
#380000
b111 5
b0 6
b11 '
b11 +
b1000 &
b1000 .
1%
#385000
b11 +
b11 *
#400000
0"
b0 !
b0 1
0%
#420000
b0 5
b1001 &
b1001 .
1%
#440000
0%
#460000
b1010 &
b1010 .
1%
#480000
0%
#500000
b1011 &
b1011 .
1%
#520000
0%
#540000
b1100 &
b1100 .
1%
#560000
0%
#580000
b1101 &
b1101 .
1%
#600000
0%
#620000
b1110 &
b1110 .
1%
#640000
0%
#660000
b1111 &
b1111 .
1%
#680000
0%
#700000
b0 &
b0 .
1%
#720000
0%
#740000
b110000000000000000000000000000000000000000000000000000000000000000 $
b110000000000000000000000000000000000000000000000000000000000000000 /
b1 &
b1 .
1%
